marsbots_eden/__init__.py
marsbots_eden/eden.py
marsbots_eden-0.1.0.dist-info/WHEEL
marsbots_eden-0.1.0.dist-info/METADATA
marsbots_eden-0.1.0.dist-info/RECORD
