Metadata-Version: 2.1
Name: marsbots_eden
Version: 0.1.0
Summary: The core framework for cool Eden bots.
Author-email: Jonathan Miller <jon@jmill.dev>
Requires-Dist: marsbots
Requires-Dist: black ; extra == "dev"
Requires-Dist: pytest ; extra == "dev"
Requires-Dist: mypy ; extra == "dev"
Requires-Dist: pre-commit ; extra == "dev"
Requires-Dist: flake8 ; extra == "dev"
Provides-Extra: dev
